es_lemmatizer/__init__.py
es_lemmatizer/data_loader.py
es_lemmatizer/data/LICENSE
es_lemmatizer/data/MM.adj
es_lemmatizer/data/MM.adv
es_lemmatizer/data/MM.int
es_lemmatizer/data/MM.nom
es_lemmatizer/data/MM.tanc
es_lemmatizer/data/MM.vaux
es_lemmatizer/data/MM.verb
es_lemmatizer-0.2.1.dist-info/METADATA
es_lemmatizer-0.2.1.dist-info/RECORD
es_lemmatizer-0.2.1.dist-info/WHEEL
es_lemmatizer-0.2.1.dist-info/top_level.txt
