Metadata-Version: 2.1
Name: es-lemmatizer
Version: 0.2.1
Summary: A spanish lemmatizer
Home-page: UNKNOWN
License: UNKNOWN
Platform: UNKNOWN
Classifier: Programming Language :: Python :: 3
Classifier: Operating System :: OS Independent
